sqlray/__init__.py
sqlray/app.py
sqlray-1.0.1.dist-info/licenses/LICENSE
sqlray-1.0.1.dist-info/METADATA
sqlray-1.0.1.dist-info/WHEEL
sqlray-1.0.1.dist-info/entry_points.txt
sqlray-1.0.1.dist-info/top_level.txt
sqlray-1.0.1.dist-info/RECORD
