Metadata-Version: 2.4
Name: sqlray
Version: 1.0.1
Summary: SQLRay is a tool that helps you optimize SQL queries using OpenAI.
Home-page: https://github.com/JoseCarlosGarcia95/sqlray
Author: Jose Carlos Garcia Ortega
Author-email: hola@josecarlos.me
Project-URL: Bug Tracker, https://github.com/JoseCarlosGarcia95/sqlray/issues
Classifier: Programming Language :: Python :: 3
Classifier: License :: OSI Approved :: MIT License
Classifier: Operating System :: OS Independent
Requires-Python: >=3.6
License-File: LICENSE
Requires-Dist: openai==1.64.0
Requires-Dist: click==8.1.7
Dynamic: author
Dynamic: author-email
Dynamic: classifier
Dynamic: description
Dynamic: description-content-type
Dynamic: home-page
Dynamic: license-file
Dynamic: project-url
Dynamic: requires-dist
Dynamic: requires-python
Dynamic: summary
